EvOAutoML/__init__.py
EvOAutoML/__version__.py
EvOAutoML/config.py
EvOAutoML/pipelinehelper.py
EvOAutoML/base/__init__.py
EvOAutoML/base/evolution.py
EvOAutoML/base/utils.py
EvOAutoML/classification/__init__.py
EvOAutoML/classification/bagging.py
EvOAutoML/regression/__init__.py
EvOAutoML/regression/bagging.py
EvOAutoML/utils/__init__.py
EvOAutoML/utils/estimator_checks.py
EvOAutoML/utils/test_estimators.py
EvOAutoML-0.0.14.dist-info/LICENSE
EvOAutoML-0.0.14.dist-info/METADATA
EvOAutoML-0.0.14.dist-info/WHEEL
EvOAutoML-0.0.14.dist-info/top_level.txt
EvOAutoML-0.0.14.dist-info/RECORD
