Metadata-Version: 2.1
Name: EvOAutoML
Version: 0.0.14
Summary: Online Automated Machine Learning for river
Home-page: https://github.com/kulbachcedric/EvoAutoML
Author: Cedric Kulbach
Author-email: cedric.kulbach@googlemail.com
License: BSD-3
Classifier: License :: OSI Approved :: BSD License
Classifier: Programming Language :: Python
Classifier: Programming Language :: Python :: 3
Classifier: Programming Language :: Python :: 3.8
Classifier: Programming Language :: Python :: 3.9
Classifier: Programming Language :: Python :: 3.10
Classifier: Programming Language :: Python :: Implementation :: CPython
Classifier: Programming Language :: Python :: Implementation :: PyPy
Requires-Python: >=3.6.0
License-File: LICENSE
Requires-Dist: numpy (~=1.23.4)
Requires-Dist: scikit-learn (==1.0.2)
Requires-Dist: scikit-surprise (==1.1.1)
Requires-Dist: pandas (~=1.3.2)
Requires-Dist: river (~=0.10.1)
Requires-Dist: tqdm (~=4.61.2)
Requires-Dist: pytest (==7.0.1)
Requires-Dist: dataclasses ; python_version == '3.8'
Provides-Extra: all
Requires-Dist: numpy (~=1.23.4) ; extra == 'all'
Requires-Dist: scikit-learn (==1.0.2) ; extra == 'all'
Requires-Dist: scikit-surprise (==1.1.1) ; extra == 'all'
Requires-Dist: pandas (~=1.3.2) ; extra == 'all'
Requires-Dist: river (~=0.10.1) ; extra == 'all'
Requires-Dist: tqdm (~=4.61.2) ; extra == 'all'
Requires-Dist: pytest (==7.0.1) ; extra == 'all'
Requires-Dist: graphviz (>=0.10.1) ; extra == 'all'
Requires-Dist: matplotlib (>=3.0.2) ; extra == 'all'
Requires-Dist: mypy (>=0.761) ; extra == 'all'
Requires-Dist: pre-commit (>=2.9.2) ; extra == 'all'
Requires-Dist: pytest (>=4.5.0) ; extra == 'all'
Requires-Dist: pytest-cov (>=2.6.1) ; extra == 'all'
Requires-Dist: scikit-learn (>=0.22.1) ; extra == 'all'
Requires-Dist: sqlalchemy (>=1.4) ; extra == 'all'
Requires-Dist: black (>=22.1.0) ; extra == 'all'
Requires-Dist: flake8 (>=4.0.1) ; extra == 'all'
Requires-Dist: isort (>=5.9.3) ; extra == 'all'
Requires-Dist: jupyter (>=1.0.0) ; extra == 'all'
Requires-Dist: pyupgrade (==3.2.0) ; extra == 'all'
Requires-Dist: flask (>=2.0.2) ; extra == 'all'
Requires-Dist: ipykernel (>=6.9.0) ; extra == 'all'
Requires-Dist: mike (>=0.5.3) ; extra == 'all'
Requires-Dist: mkdocs (>=1.2.3) ; extra == 'all'
Requires-Dist: mkdocs-awesome-pages-plugin (>=2.7.0) ; extra == 'all'
Requires-Dist: mkdocs-gen-files (>=0.3.5) ; extra == 'all'
Requires-Dist: mkdocs-literate-nav (>=0.4.1) ; extra == 'all'
Requires-Dist: mkdocs-material (>=8.1.11) ; extra == 'all'
Requires-Dist: mkdocstrings[python] (>=0.19.0) ; extra == 'all'
Requires-Dist: pytkdocs[numpy-style] (>=0.5.0) ; extra == 'all'
Requires-Dist: ipython-genutils (>=0.1.0) ; extra == 'all'
Requires-Dist: mkdocs-jupyter (>=0.20.0) ; extra == 'all'
Requires-Dist: nbconvert (>=6.4.2) ; extra == 'all'
Requires-Dist: numpydoc (>=1.2) ; extra == 'all'
Requires-Dist: spacy (>=3.2.2) ; extra == 'all'
Requires-Dist: jinja2 (>=3.0.3) ; extra == 'all'
Provides-Extra: dev
Requires-Dist: numpy (~=1.23.4) ; extra == 'dev'
Requires-Dist: scikit-learn (==1.0.2) ; extra == 'dev'
Requires-Dist: scikit-surprise (==1.1.1) ; extra == 'dev'
Requires-Dist: pandas (~=1.3.2) ; extra == 'dev'
Requires-Dist: river (~=0.10.1) ; extra == 'dev'
Requires-Dist: tqdm (~=4.61.2) ; extra == 'dev'
Requires-Dist: pytest (==7.0.1) ; extra == 'dev'
Requires-Dist: graphviz (>=0.10.1) ; extra == 'dev'
Requires-Dist: matplotlib (>=3.0.2) ; extra == 'dev'
Requires-Dist: mypy (>=0.761) ; extra == 'dev'
Requires-Dist: pre-commit (>=2.9.2) ; extra == 'dev'
Requires-Dist: pytest (>=4.5.0) ; extra == 'dev'
Requires-Dist: pytest-cov (>=2.6.1) ; extra == 'dev'
Requires-Dist: scikit-learn (>=0.22.1) ; extra == 'dev'
Requires-Dist: sqlalchemy (>=1.4) ; extra == 'dev'
Requires-Dist: black (>=22.1.0) ; extra == 'dev'
Requires-Dist: flake8 (>=4.0.1) ; extra == 'dev'
Requires-Dist: isort (>=5.9.3) ; extra == 'dev'
Requires-Dist: jupyter (>=1.0.0) ; extra == 'dev'
Requires-Dist: pyupgrade (==3.2.0) ; extra == 'dev'
Provides-Extra: docs
Requires-Dist: flask (>=2.0.2) ; extra == 'docs'
Requires-Dist: ipykernel (>=6.9.0) ; extra == 'docs'
Requires-Dist: mike (>=0.5.3) ; extra == 'docs'
Requires-Dist: mkdocs (>=1.2.3) ; extra == 'docs'
Requires-Dist: mkdocs-awesome-pages-plugin (>=2.7.0) ; extra == 'docs'
Requires-Dist: mkdocs-gen-files (>=0.3.5) ; extra == 'docs'
Requires-Dist: mkdocs-literate-nav (>=0.4.1) ; extra == 'docs'
Requires-Dist: mkdocs-material (>=8.1.11) ; extra == 'docs'
Requires-Dist: mkdocstrings[python] (>=0.19.0) ; extra == 'docs'
Requires-Dist: pytkdocs[numpy-style] (>=0.5.0) ; extra == 'docs'
Requires-Dist: ipython-genutils (>=0.1.0) ; extra == 'docs'
Requires-Dist: mkdocs-jupyter (>=0.20.0) ; extra == 'docs'
Requires-Dist: nbconvert (>=6.4.2) ; extra == 'docs'
Requires-Dist: numpydoc (>=1.2) ; extra == 'docs'
Requires-Dist: spacy (>=3.2.2) ; extra == 'docs'
Requires-Dist: jinja2 (>=3.0.3) ; extra == 'docs'
